codebase/__init__.py
codebase/augment_text.py
codebase/eval_zero_shot_clip.py
codebase/metrics.py
codebase/train.py
codebase/train_classifier.py
codebase/train_detector.py
codebase/utils.py
codebase/Classifiers/__init__.py
codebase/Classifiers/experiments.py
codebase/Classifiers/models/__init__.py
codebase/Classifiers/models/breast_clip_classifier.py
codebase/Datasets/__init__.py
codebase/Datasets/dataset_concepts.py
codebase/Datasets/dataset_utils.py
codebase/Detectors/__init__.py
codebase/Detectors/detectors_utils.py
codebase/Detectors/experiments.py
codebase/Detectors/retinanet/__init__.py
codebase/Detectors/retinanet/anchors.py
codebase/Detectors/retinanet/detector_model.py
codebase/Detectors/retinanet/efficient_net.py
codebase/Detectors/retinanet/efficientnet_utils.py
codebase/Detectors/retinanet/losses.py
codebase/breastclip/__init__.py
codebase/breastclip/evaluator.py
codebase/breastclip/trainer.py
codebase/breastclip/trainer_ddp.py
codebase/breastclip/validator.py
codebase/breastclip/data/__init__.py
codebase/breastclip/data/data_utils.py
codebase/breastclip/data/datamodule.py
codebase/breastclip/data/datasets/__init__.py
codebase/breastclip/data/datasets/image_aligner.py
codebase/breastclip/data/datasets/image_classification.py
codebase/breastclip/data/datasets/image_classification_zs.py
codebase/breastclip/data/datasets/imagetext.py
codebase/breastclip/data/datasets/imagetext_contrastive.py
codebase/breastclip/data/datasets/imagetext_retrieval.py
codebase/breastclip/data/datasets/imagetext_zz.py
codebase/breastclip/data/datasets/prompts.json
codebase/breastclip/data/datasets/prompts_all.json
codebase/breastclip/loss/__init__.py
codebase/breastclip/loss/breast_clip.py
codebase/breastclip/loss/breast_clip_contrastive.py
codebase/breastclip/loss/classification.py
codebase/breastclip/loss/combined_loss.py
codebase/breastclip/model/__init__.py
codebase/breastclip/model/clip.py
codebase/breastclip/model/image_classification.py
mammoclip-0.1.8.dist-info/licenses/LICENSE.txt
mammoclip-0.1.8.dist-info/METADATA
mammoclip-0.1.8.dist-info/WHEEL
mammoclip-0.1.8.dist-info/entry_points.txt
mammoclip-0.1.8.dist-info/top_level.txt
mammoclip-0.1.8.dist-info/RECORD
