Metadata-Version: 2.4
Name: mammoclip
Version: 0.1.8
Summary: Mammo-CLIP: A Vision Language Foundation Model to Enhance Data Efficiency and Robustness in Mammography
Home-page: https://github.com/mammoclip/mammoclip
Author: Mammo-CLIP Team
Author-email: contact@mammoclip.com
License: MIT
Project-URL: Repository, https://github.com/batmanlab/Mammo-CLIP
Project-URL: Original Paper, https://arxiv.org/abs/2409.03675
Project-URL: Bug Tracker, https://github.com/batmanlab/Mammo-CLIP/issues
Keywords: mammography,clip,medical-imaging,deep-learning,computer-vision
Classifier: Development Status :: 3 - Alpha
Classifier: Intended Audience :: Developers
Classifier: Intended Audience :: Science/Research
Classifier: License :: OSI Approved :: MIT License
Classifier: Operating System :: OS Independent
Classifier: Programming Language :: Python :: 3
Classifier: Programming Language :: Python :: 3.8
Classifier: Programming Language :: Python :: 3.9
Classifier: Programming Language :: Python :: 3.10
Classifier: Programming Language :: Python :: 3.11
Classifier: Topic :: Scientific/Engineering :: Artificial Intelligence
Classifier: Topic :: Scientific/Engineering :: Medical Science Apps.
Requires-Python: >=3.8
License-File: LICENSE.txt
Requires-Dist: torch>=1.9.0
Requires-Dist: torchvision>=0.10.0
Requires-Dist: transformers>=4.20.0
Requires-Dist: numpy>=1.20.0
Requires-Dist: opencv-python>=4.5.0
Requires-Dist: pillow>=8.0.0
Requires-Dist: scipy>=1.7.0
Requires-Dist: dicomsdl>=0.109.0
Requires-Dist: omegaconf>=2.1.0
Requires-Dist: huggingface-hub>=0.10.0
Requires-Dist: safetensors>=0.3.0
Requires-Dist: albumentations>=1.0.0
Requires-Dist: pandas>=1.0.0
Requires-Dist: scikit-learn>=0.24.0
Requires-Dist: timm>=0.6.0
Provides-Extra: dev
Requires-Dist: pytest>=6.0; extra == "dev"
Requires-Dist: pytest-cov>=2.0; extra == "dev"
Requires-Dist: black>=21.0; extra == "dev"
Requires-Dist: isort>=5.0; extra == "dev"
Requires-Dist: flake8>=3.8; extra == "dev"
Provides-Extra: training
Requires-Dist: albumentations>=1.0.0; extra == "training"
Requires-Dist: pandas>=1.3.0; extra == "training"
Requires-Dist: scikit-learn>=1.0.0; extra == "training"
Requires-Dist: matplotlib>=3.5.0; extra == "training"
Dynamic: author-email
Dynamic: home-page
Dynamic: license-file
Dynamic: requires-python
